mininear/__init__.py
mininear/_conv.py
mininear/encoder.py
mininear/layers.py
mininear/utils.py
mininear/weights.npz
mininear-0.1.0.dist-info/licenses/COPYING
mininear-0.1.0.dist-info/METADATA
mininear-0.1.0.dist-info/WHEEL
mininear-0.1.0.dist-info/top_level.txt
mininear-0.1.0.dist-info/RECORD
