Metadata-Version: 2.4
Name: mininear
Version: 0.1.0
Summary: A NumPy port of the NEAR code for embedding protein sequences.
Author-email: Martin Larralde <martin.larralde@embl.de>
License:                     GNU GENERAL PUBLIC LICENSE
Project-URL: Bug Tracker, https://github.com/althonos/mininear/issues
Project-URL: Changelog, https://github.com/althonos/mininear/blob/master/CHANGELOG.md
Project-URL: Coverage, https://codecov.io/gh/althonos/mininear/
Project-URL: Builds, https://github.com/althonos/mininear/actions
Project-URL: PyPI, https://pypi.org/project/mininear
Keywords: bioinformatics,protein,sequence,embedding
Classifier: Development Status :: 4 - Beta
Classifier: Intended Audience :: Developers
Classifier: Intended Audience :: Science/Research
Classifier: License :: OSI Approved :: GNU General Public License v3 or later (GPLv3+)
Classifier: Operating System :: OS Independent
Classifier: Programming Language :: Python :: 3
Classifier: Topic :: Scientific/Engineering :: Bio-Informatics
Classifier: Topic :: Scientific/Engineering :: Medical Science Apps.
Classifier: Topic :: Software Development :: Libraries :: Python Modules
Classifier: Typing :: Typed
Requires-Python: >=3.7
License-File: COPYING
Requires-Dist: numpy>=1.0
Dynamic: license-file
